src/__init__.py
src/config.py
src/main.py
src/services/__init__.py
src/services/budget_manager.py
src/services/cache.py
src/services/data_processor.py
src/services/dune_client.py
src/services/error_analyzer.py
src/tools/__init__.py
dune_mcp-0.1.2.dist-info/METADATA
dune_mcp-0.1.2.dist-info/WHEEL
dune_mcp-0.1.2.dist-info/entry_points.txt
dune_mcp-0.1.2.dist-info/RECORD
