Metadata-Version: 2.4
Name: dune-mcp
Version: 0.1.2
Summary: A defensive, token-aware MCP server for Dune Analytics.
Author-email: nice-bills <alnicewilliams2@gmail.com>
Requires-Python: >=3.12
Requires-Dist: cachetools>=6.2.4
Requires-Dist: curl-cffi>=0.14.0
Requires-Dist: dune-client>=1.10.0
Requires-Dist: mcp[cli]>=1.24.0
Requires-Dist: pandas>=2.3.3
Requires-Dist: pydantic>=2.12.5
Requires-Dist: python-dotenv>=1.2.1
Requires-Dist: requests>=2.32.5
